hplrv/__init__.py
hplrv/constants.py
hplrv/monitors.py
hplrv/rendering.py
hplrv/templates/absence.python.jinja
hplrv/templates/common.python.jinja
hplrv/templates/existence.python.jinja
hplrv/templates/node.python.jinja
hplrv/templates/predicates.python.jinja
hplrv/templates/prevention.python.jinja
hplrv/templates/requirement-refs.python.jinja
hplrv/templates/requirement-simple.python.jinja
hplrv/templates/response.python.jinja
hpl_rv_gen-0.2.0.dist-info/LICENSE
hpl_rv_gen-0.2.0.dist-info/METADATA
hpl_rv_gen-0.2.0.dist-info/WHEEL
hpl_rv_gen-0.2.0.dist-info/top_level.txt
hpl_rv_gen-0.2.0.dist-info/RECORD
