Metadata-Version: 2.1
Name: hpl-rv-gen
Version: 0.2.0
Summary: Runtime monitor generator based on HPL properties
Home-page: https://github.com/git-afsantos/hpl-rv-gen
Author: André Santos
Author-email: andre.f.santos@inesctec.pt
License: MIT
Keywords: haros ros runtime-verification runtime-monitoring
Platform: UNKNOWN
Classifier: Development Status :: 4 - Beta
Classifier: Intended Audience :: Developers
Classifier: Intended Audience :: Science/Research
Classifier: License :: OSI Approved :: MIT License
Classifier: Operating System :: OS Independent
Classifier: Programming Language :: Python
Classifier: Programming Language :: Python :: 2
Classifier: Programming Language :: Python :: 2.7
Classifier: Programming Language :: Python :: 3
Classifier: Programming Language :: Python :: 3.5
Classifier: Programming Language :: Python :: 3.6
Classifier: Programming Language :: Python :: 3.7
Classifier: Programming Language :: Python :: 3.8
Classifier: Programming Language :: Python :: 3.9
Classifier: Programming Language :: Python :: 3.10
Classifier: Topic :: Scientific/Engineering
Classifier: Topic :: Software Development
Classifier: Topic :: Software Development :: Code Generators
Classifier: Topic :: Software Development :: Libraries
Classifier: Topic :: Software Development :: Libraries :: Python Modules
Classifier: Topic :: Software Development :: Quality Assurance
Requires-Python: >=2.7, !=3.0.*, !=3.1.*, !=3.2.*, !=3.3.*, !=3.4.*
Requires-Dist: future
Requires-Dist: hpl-specs (<1.0.0)
Requires-Dist: Jinja2 (>=2.10.0)
